cqc_quam_state/__init__.py
cqc_quam_state/cli.py
cqc_quam_state/utils.py
cqc_quam_state-2026.2.1.data/scripts/load-cqc-quam
quam_state/__init__.py
quam_state/state.json
quam_state/wiring.json
cqc_quam_state-2026.2.1.dist-info/METADATA
cqc_quam_state-2026.2.1.dist-info/WHEEL
cqc_quam_state-2026.2.1.dist-info/entry_points.txt
cqc_quam_state-2026.2.1.dist-info/top_level.txt
cqc_quam_state-2026.2.1.dist-info/RECORD
