Metadata-Version: 2.4
Name: cqc-quam-state
Version: 2026.2.1
Summary: Add your description here
Author-email: JUNIQ Software Team <info-juniq@fz-juelich.de>
License: MIT
Project-URL: Homepage, https://gitlab.jsc.fz-juelich.de/qip/cqc/cqc-quam-state
Project-URL: Repository, https://gitlab.jsc.fz-juelich.de/qip/cqc/cqc-quam-state
Classifier: Development Status :: 3 - Alpha
Classifier: Intended Audience :: Developers
Classifier: License :: OSI Approved :: MIT License
Classifier: Programming Language :: Python :: 3
Classifier: Programming Language :: Python :: 3.11
Requires-Python: >=3.11
Requires-Dist: click>=8.0.0
